fw_gear_project_settings/__init__.py
fw_gear_project_settings/main.py
fw_gear_project_settings/parser.py
fw_gear_project_settings/utils.py
fw_gear_project_settings-2.2.6.dist-info/LICENSE
fw_gear_project_settings-2.2.6.dist-info/METADATA
fw_gear_project_settings-2.2.6.dist-info/WHEEL
fw_gear_project_settings-2.2.6.dist-info/RECORD
