Metadata-Version: 2.1
Name: fw-gear-project-settings
Version: 2.2.6
Summary: For a given project, clone the permissions and gear rules to a new project, or export the settings for import to another project.
Home-page: https://gitlab.com/flywheel-io/scientific-solutions/gears/project-settings
License: MIT
Keywords: Flywheel,Gears
Author: Flywheel
Author-email: support@flywheel.io
Requires-Python: >=3.11,<4.0
Classifier: License :: OSI Approved :: MIT License
Classifier: Programming Language :: Python :: 3
Classifier: Programming Language :: Python :: 3.11
Classifier: Programming Language :: Python :: 3.12
Classifier: Topic :: Scientific/Engineering
Requires-Dist: flywheel-gear-toolkit (>=0.6.13,<0.7.0)
Requires-Dist: flywheel-sdk (>=17.4.0,<18.0.0)
Requires-Dist: glob2 (>=0.7,<0.8)
Project-URL: Repository, https://gitlab.com/flywheel-io/scientific-solutions/gears/project-settings
